[
    {
        "text":"Assertive",
        "suggeg":"when we are able to express needs confidently and respectfully"
    },
    {
        "text":"Rapport building",
        "suggeg":"when we are curious about others and value connection."
    },
    
    {
        "text":"Empathy",
        "suggeg":"when we are able to understand what others’ need through compassion."
    },
    
    {
        "text":"Flexibility",
        "suggeg":"When we are open-minded about what is possible and are willing to adapt to allow contentment for all."
    },
    
    {
        "text":"Intuition",
        "suggeg":"When we feel that our heart knows the best way forward and listen to that feeling."
    },
     {
        "text":"Trust",
        "suggeg":"When we believe in ourselves and others for something to succeed."
    }
]